simplyRSA/__init__.py
simplyRSA/roiRSA.py
simplyRSA/searchlight.py
simplyrsa-1.51.dist-info/METADATA
simplyrsa-1.51.dist-info/WHEEL
simplyrsa-1.51.dist-info/top_level.txt
simplyrsa-1.51.dist-info/RECORD
