Metadata-Version: 2.4
Name: simplyRSA
Version: 1.51
Summary: Simple package for RSA analyses
Home-page: https://github.com/AbrahamSV/simplyRSA/
Author: Abraham Sanchez
Author-email: abrahamss.av@gmail.com
Dynamic: author
Dynamic: author-email
Dynamic: description
Dynamic: description-content-type
Dynamic: home-page
Dynamic: summary
